<BackupInst xmlns="http://www.microsoft.com/GroupPolicy/GPOOperations/Manifest"><GPOGuid><![CDATA[{346600b4-2849-40d9-a115-b19f345be1ec}]]></GPOGuid><GPODomain><![CDATA[bcl.nu]]></GPODomain><GPODomainGuid><![CDATA[{f5c5e011-a444-44d5-8809-c86e2683e8a9}]]></GPODomainGuid><GPODomainController><![CDATA[dc02.bcl.nu]]></GPODomainController><BackupTime><![CDATA[2021-09-16T17:19:28]]></BackupTime><ID><![CDATA[{0C906B29-638E-473C-B1D7-06E1ACC21254}]]></ID><Comment><![CDATA[]]></Comment><GPODisplayName><![CDATA[Bcl - Computer - User Rights Assignment - Web Server]]></GPODisplayName></BackupInst>
