<Backups xmlns="http://www.microsoft.com/GroupPolicy/GPOOperations/Manifest" xmlns:mfst="http://www.microsoft.com/GroupPolicy/GPOOperations/Manifest" mfst:version="1.0"><BackupInst><GPOGuid><![CDATA[{ff9c0aaa-e6be-4a6a-b7b3-07ee652a2670}]]></GPOGuid><GPODomain><![CDATA[bcl.nu]]></GPODomain><GPODomainGuid><![CDATA[{f5c5e011-a444-44d5-8809-c86e2683e8a9}]]></GPODomainGuid><GPODomainController><![CDATA[dc02.bcl.nu]]></GPODomainController><BackupTime><![CDATA[2021-02-05T11:27:43]]></BackupTime><ID><![CDATA[{62F5E41D-8AA8-4272-AC4C-33B461BC1330}]]></ID><Comment><![CDATA[]]></Comment><GPODisplayName><![CDATA[Bcl - User - Display Settings]]></GPODisplayName></BackupInst><BackupInst><GPOGuid><![CDATA[{f70870fa-8850-402f-84b3-6905011466d4}]]></GPOGuid><GPODomain><![CDATA[bcl.nu]]></GPODomain><GPODomainGuid><![CDATA[{f5c5e011-a444-44d5-8809-c86e2683e8a9}]]></GPODomainGuid><GPODomainController><![CDATA[dc02.bcl.nu]]></GPODomainController><BackupTime><![CDATA[2021-02-05T11:27:43]]></BackupTime><ID><![CDATA[{E18679AD-9C20-4D9B-8EBB-08C9FB575788}]]></ID><Comment><![CDATA[]]></Comment><GPODisplayName><![CDATA[Bcl - Computer - Disable LLMNR]]></GPODisplayName></BackupInst><BackupInst><GPOGuid><![CDATA[{ed0f9373-1d69-4703-aed2-0d4669c46ac1}]]></GPOGuid><GPODomain><![CDATA[bcl.nu]]></GPODomain><GPODomainGuid><![CDATA[{f5c5e011-a444-44d5-8809-c86e2683e8a9}]]></GPODomainGuid><GPODomainController><![CDATA[dc02.bcl.nu]]></GPODomainController><BackupTime><![CDATA[2021-02-05T11:27:43]]></BackupTime><ID><![CDATA[{FD7D761D-91A5-4A15-AF41-F022A55DB01A}]]></ID><Comment><![CDATA[]]></Comment><GPODisplayName><![CDATA[Bcl - Computer - Disable WPAD]]></GPODisplayName></BackupInst><BackupInst><GPOGuid><![CDATA[{e0d35fce-2651-446b-9b46-8440909e0608}]]></GPOGuid><GPODomain><![CDATA[bcl.nu]]></GPODomain><GPODomainGuid><![CDATA[{f5c5e011-a444-44d5-8809-c86e2683e8a9}]]></GPODomainGuid><GPODomainController><![CDATA[dc02.bcl.nu]]></GPODomainController><BackupTime><![CDATA[2021-02-05T11:27:42]]></BackupTime><ID><![CDATA[{A2AAED9A-3643-4715-8D23-17B3448FFF13}]]></ID><Comment><![CDATA[]]></Comment><GPODisplayName><![CDATA[Bcl - Computer - Firewall - IPSec - Any - Require/Request]]></GPODisplayName></BackupInst><BackupInst><GPOGuid><![CDATA[{d778074a-ccfe-4ba9-b509-068f84e535a8}]]></GPOGuid><GPODomain><![CDATA[bcl.nu]]></GPODomain><GPODomainGuid><![CDATA[{f5c5e011-a444-44d5-8809-c86e2683e8a9}]]></GPODomainGuid><GPODomainController><![CDATA[dc02.bcl.nu]]></GPODomainController><BackupTime><![CDATA[2021-02-05T11:27:42]]></BackupTime><ID><![CDATA[{BF263FAA-835B-4691-A02D-C2D167EF289B}]]></ID><Comment><![CDATA[]]></Comment><GPODisplayName><![CDATA[Bcl - User - Disable WSH]]></GPODisplayName></BackupInst><BackupInst><GPOGuid><![CDATA[{d0b96dd3-ef07-4c56-aa08-b5ec030f2305}]]></GPOGuid><GPODomain><![CDATA[bcl.nu]]></GPODomain><GPODomainGuid><![CDATA[{f5c5e011-a444-44d5-8809-c86e2683e8a9}]]></GPODomainGuid><GPODomainController><![CDATA[dc02.bcl.nu]]></GPODomainController><BackupTime><![CDATA[2021-02-05T11:27:42]]></BackupTime><ID><![CDATA[{4080110B-CD54-4223-8FAA-950554D81EAF}]]></ID><Comment><![CDATA[]]></Comment><GPODisplayName><![CDATA[Bcl - Domain Controller - Time - PDC NTP]]></GPODisplayName></BackupInst><BackupInst><GPOGuid><![CDATA[{ce7f337c-3fd0-48da-b4ef-8e2cb3b65d5b}]]></GPOGuid><GPODomain><![CDATA[bcl.nu]]></GPODomain><GPODomainGuid><![CDATA[{f5c5e011-a444-44d5-8809-c86e2683e8a9}]]></GPODomainGuid><GPODomainController><![CDATA[dc02.bcl.nu]]></GPODomainController><BackupTime><![CDATA[2021-02-05T11:27:41]]></BackupTime><ID><![CDATA[{80728994-D58D-48E9-88A9-027203883201}]]></ID><Comment><![CDATA[]]></Comment><GPODisplayName><![CDATA[Bcl - Computer - Enable LSA Protection & Audit]]></GPODisplayName></BackupInst><BackupInst><GPOGuid><![CDATA[{c844173f-7b3d-4199-b545-c9993ea91ca8}]]></GPOGuid><GPODomain><![CDATA[bcl.nu]]></GPODomain><GPODomainGuid><![CDATA[{f5c5e011-a444-44d5-8809-c86e2683e8a9}]]></GPODomainGuid><GPODomainController><![CDATA[dc02.bcl.nu]]></GPODomainController><BackupTime><![CDATA[2021-02-05T11:27:41]]></BackupTime><ID><![CDATA[{1421D721-811C-4AE6-A07D-ABC674498898}]]></ID><Comment><![CDATA[]]></Comment><GPODisplayName><![CDATA[Bcl - Computer - Enable SMB Encryption]]></GPODisplayName></BackupInst><BackupInst><GPOGuid><![CDATA[{bed89586-0d81-4f29-883a-20d239cd0546}]]></GPOGuid><GPODomain><![CDATA[bcl.nu]]></GPODomain><GPODomainGuid><![CDATA[{f5c5e011-a444-44d5-8809-c86e2683e8a9}]]></GPODomainGuid><GPODomainController><![CDATA[dc02.bcl.nu]]></GPODomainController><BackupTime><![CDATA[2021-02-05T11:27:40]]></BackupTime><ID><![CDATA[{7F5801C5-A43C-40FB-AC8F-272DDBC52971}]]></ID><Comment><![CDATA[]]></Comment><GPODisplayName><![CDATA[Bcl - Computer - Intranet]]></GPODisplayName></BackupInst><BackupInst><GPOGuid><![CDATA[{bd617c09-4803-452d-b7b2-947d39a872fd}]]></GPOGuid><GPODomain><![CDATA[bcl.nu]]></GPODomain><GPODomainGuid><![CDATA[{f5c5e011-a444-44d5-8809-c86e2683e8a9}]]></GPODomainGuid><GPODomainController><![CDATA[dc02.bcl.nu]]></GPODomainController><BackupTime><![CDATA[2021-02-05T11:27:40]]></BackupTime><ID><![CDATA[{097F216C-D054-453D-B912-CD064A41C3CF}]]></ID><Comment><![CDATA[]]></Comment><GPODisplayName><![CDATA[Bcl - Computer - Auditing - Certification Services]]></GPODisplayName></BackupInst><BackupInst><GPOGuid><![CDATA[{bbe09dad-37d1-4218-908e-f020146999ae}]]></GPOGuid><GPODomain><![CDATA[bcl.nu]]></GPODomain><GPODomainGuid><![CDATA[{f5c5e011-a444-44d5-8809-c86e2683e8a9}]]></GPODomainGuid><GPODomainController><![CDATA[dc02.bcl.nu]]></GPODomainController><BackupTime><![CDATA[2021-02-05T11:27:40]]></BackupTime><ID><![CDATA[{B3E8B23E-F463-4084-8A94-DF74C0AFDB0E}]]></ID><Comment><![CDATA[]]></Comment><GPODisplayName><![CDATA[Bcl - Computer - Enable Virtualization Based Security]]></GPODisplayName></BackupInst><BackupInst><GPOGuid><![CDATA[{bbddf5e8-823f-4715-b247-cc1975252845}]]></GPOGuid><GPODomain><![CDATA[bcl.nu]]></GPODomain><GPODomainGuid><![CDATA[{f5c5e011-a444-44d5-8809-c86e2683e8a9}]]></GPODomainGuid><GPODomainController><![CDATA[dc02.bcl.nu]]></GPODomainController><BackupTime><![CDATA[2021-02-05T11:27:40]]></BackupTime><ID><![CDATA[{B8B055F7-4259-481D-BEAE-1D58D7AE6E87}]]></ID><Comment><![CDATA[]]></Comment><GPODisplayName><![CDATA[Bcl - Computer - Firewall - IPSec - 80 (TCP) - Disable Private and Public]]></GPODisplayName></BackupInst><BackupInst><GPOGuid><![CDATA[{b10a8124-faaa-459c-a1aa-7ff6464973bc}]]></GPOGuid><GPODomain><![CDATA[bcl.nu]]></GPODomain><GPODomainGuid><![CDATA[{f5c5e011-a444-44d5-8809-c86e2683e8a9}]]></GPODomainGuid><GPODomainController><![CDATA[dc02.bcl.nu]]></GPODomainController><BackupTime><![CDATA[2021-02-05T11:27:39]]></BackupTime><ID><![CDATA[{30E705C3-80F4-4692-9BA9-5335DF5B3945}]]></ID><Comment><![CDATA[]]></Comment><GPODisplayName><![CDATA[Bcl - Domain - Force Group Policy]]></GPODisplayName></BackupInst><BackupInst><GPOGuid><![CDATA[{a7e54793-bb46-42fa-bc07-f69784ac2382}]]></GPOGuid><GPODomain><![CDATA[bcl.nu]]></GPODomain><GPODomainGuid><![CDATA[{f5c5e011-a444-44d5-8809-c86e2683e8a9}]]></GPODomainGuid><GPODomainController><![CDATA[dc02.bcl.nu]]></GPODomainController><BackupTime><![CDATA[2021-02-05T11:27:39]]></BackupTime><ID><![CDATA[{1C2B3A81-3C57-4472-B4A8-994C591F12FC}]]></ID><Comment><![CDATA[]]></Comment><GPODisplayName><![CDATA[Bcl - Computer - Firewall - IPSec - 443 (TCP) - Request]]></GPODisplayName></BackupInst><BackupInst><GPOGuid><![CDATA[{98e114b5-b5d0-465c-ad4c-e86fe498223c}]]></GPOGuid><GPODomain><![CDATA[bcl.nu]]></GPODomain><GPODomainGuid><![CDATA[{f5c5e011-a444-44d5-8809-c86e2683e8a9}]]></GPODomainGuid><GPODomainController><![CDATA[dc02.bcl.nu]]></GPODomainController><BackupTime><![CDATA[2021-02-05T11:27:39]]></BackupTime><ID><![CDATA[{4F404F3D-9EB5-47DD-8A16-88AF6459DE29}]]></ID><Comment><![CDATA[]]></Comment><GPODisplayName><![CDATA[Bcl - Computer - Require Client LDAP Signing]]></GPODisplayName></BackupInst><BackupInst><GPOGuid><![CDATA[{9376dcc1-3311-4156-bb81-6ac63bd6fcb6}]]></GPOGuid><GPODomain><![CDATA[bcl.nu]]></GPODomain><GPODomainGuid><![CDATA[{f5c5e011-a444-44d5-8809-c86e2683e8a9}]]></GPODomainGuid><GPODomainController><![CDATA[dc02.bcl.nu]]></GPODomainController><BackupTime><![CDATA[2021-02-05T11:27:38]]></BackupTime><ID><![CDATA[{A6E8283A-5436-4B3F-8723-B8EB6CCA5B11}]]></ID><Comment><![CDATA[]]></Comment><GPODisplayName><![CDATA[Bcl - Computer - Disable Netbios]]></GPODisplayName></BackupInst><BackupInst><GPOGuid><![CDATA[{7af7fd37-13db-42a9-884d-d2d99a064cc8}]]></GPOGuid><GPODomain><![CDATA[bcl.nu]]></GPODomain><GPODomainGuid><![CDATA[{f5c5e011-a444-44d5-8809-c86e2683e8a9}]]></GPODomainGuid><GPODomainController><![CDATA[dc02.bcl.nu]]></GPODomainController><BackupTime><![CDATA[2021-02-05T11:27:38]]></BackupTime><ID><![CDATA[{42B06AC7-7085-4B3A-B578-4F49F2126B2E}]]></ID><Comment><![CDATA[]]></Comment><GPODisplayName><![CDATA[Bcl - Computer - Firewall - IPSec - 443 (TCP) - Disable Private and Public]]></GPODisplayName></BackupInst><BackupInst><GPOGuid><![CDATA[{542a67eb-9045-40ee-878e-d3ce645b3e51}]]></GPOGuid><GPODomain><![CDATA[bcl.nu]]></GPODomain><GPODomainGuid><![CDATA[{f5c5e011-a444-44d5-8809-c86e2683e8a9}]]></GPODomainGuid><GPODomainController><![CDATA[dc02.bcl.nu]]></GPODomainController><BackupTime><![CDATA[2021-02-05T11:27:38]]></BackupTime><ID><![CDATA[{B5F152F6-2329-4C1E-B5A9-32F725960390}]]></ID><Comment><![CDATA[]]></Comment><GPODisplayName><![CDATA[Bcl - Computer - Disable Telemetry]]></GPODisplayName></BackupInst><BackupInst><GPOGuid><![CDATA[{520eebd9-22ff-4007-a17c-57344559bd52}]]></GPOGuid><GPODomain><![CDATA[bcl.nu]]></GPODomain><GPODomainGuid><![CDATA[{f5c5e011-a444-44d5-8809-c86e2683e8a9}]]></GPODomainGuid><GPODomainController><![CDATA[dc02.bcl.nu]]></GPODomainController><BackupTime><![CDATA[2021-02-05T11:27:37]]></BackupTime><ID><![CDATA[{B060BC90-4C48-4F1F-8120-20EA70AF46E3}]]></ID><Comment><![CDATA[]]></Comment><GPODisplayName><![CDATA[Bcl - Domain - Certificate Services Client]]></GPODisplayName></BackupInst><BackupInst><GPOGuid><![CDATA[{4e373035-6cd4-4cb8-afac-f3de6de0ef95}]]></GPOGuid><GPODomain><![CDATA[bcl.nu]]></GPODomain><GPODomainGuid><![CDATA[{f5c5e011-a444-44d5-8809-c86e2683e8a9}]]></GPODomainGuid><GPODomainController><![CDATA[dc02.bcl.nu]]></GPODomainController><BackupTime><![CDATA[2021-02-05T11:27:37]]></BackupTime><ID><![CDATA[{BA5FF9CB-C210-423D-B58D-AACE6899BB7D}]]></ID><Comment><![CDATA[]]></Comment><GPODisplayName><![CDATA[Bcl - Domain Controller - Time - Non-PDC]]></GPODisplayName></BackupInst><BackupInst><GPOGuid><![CDATA[{4c03002d-127d-491c-94a7-1c216c718b53}]]></GPOGuid><GPODomain><![CDATA[bcl.nu]]></GPODomain><GPODomainGuid><![CDATA[{f5c5e011-a444-44d5-8809-c86e2683e8a9}]]></GPODomainGuid><GPODomainController><![CDATA[dc02.bcl.nu]]></GPODomainController><BackupTime><![CDATA[2021-02-05T11:27:37]]></BackupTime><ID><![CDATA[{91D28E83-8AA7-4AD3-91CB-A83C8E7F7E47}]]></ID><Comment><![CDATA[]]></Comment><GPODisplayName><![CDATA[Bcl - Computer - Enforce Netlogon Full Secure Channel Protection]]></GPODisplayName></BackupInst><BackupInst><GPOGuid><![CDATA[{43f3c285-e3ec-492d-a87e-9e21c51aa7d6}]]></GPOGuid><GPODomain><![CDATA[bcl.nu]]></GPODomain><GPODomainGuid><![CDATA[{f5c5e011-a444-44d5-8809-c86e2683e8a9}]]></GPODomainGuid><GPODomainController><![CDATA[dc02.bcl.nu]]></GPODomainController><BackupTime><![CDATA[2021-02-05T11:27:37]]></BackupTime><ID><![CDATA[{5C294A96-07A7-4BC4-88A3-F0FD31AEA3A6}]]></ID><Comment><![CDATA[]]></Comment><GPODisplayName><![CDATA[Bcl - User - Disable WPAD]]></GPODisplayName></BackupInst><BackupInst><GPOGuid><![CDATA[{401e1bcc-3604-49a4-b432-355c02d42790}]]></GPOGuid><GPODomain><![CDATA[bcl.nu]]></GPODomain><GPODomainGuid><![CDATA[{f5c5e011-a444-44d5-8809-c86e2683e8a9}]]></GPODomainGuid><GPODomainController><![CDATA[dc02.bcl.nu]]></GPODomainController><BackupTime><![CDATA[2021-02-05T11:27:36]]></BackupTime><ID><![CDATA[{C9B57DEE-04E6-4D85-AB9B-9CC5B1FF8B2E}]]></ID><Comment><![CDATA[]]></Comment><GPODisplayName><![CDATA[Bcl - Computer - Firewall - IPSec - 80 (TCP) - Request]]></GPODisplayName></BackupInst><BackupInst><GPOGuid><![CDATA[{32b021c5-5396-49fd-9d4a-aaaae2333fb7}]]></GPOGuid><GPODomain><![CDATA[bcl.nu]]></GPODomain><GPODomainGuid><![CDATA[{f5c5e011-a444-44d5-8809-c86e2683e8a9}]]></GPODomainGuid><GPODomainController><![CDATA[dc02.bcl.nu]]></GPODomainController><BackupTime><![CDATA[2021-02-05T11:27:36]]></BackupTime><ID><![CDATA[{F0C7A416-2B32-4236-A4E8-0CEFA29A4FEA}]]></ID><Comment><![CDATA[]]></Comment><GPODisplayName><![CDATA[Bcl - Computer - Windows Update]]></GPODisplayName></BackupInst><BackupInst><GPOGuid><![CDATA[{21f55b9d-f60a-41d0-a145-3c8ecbd7463c}]]></GPOGuid><GPODomain><![CDATA[bcl.nu]]></GPODomain><GPODomainGuid><![CDATA[{f5c5e011-a444-44d5-8809-c86e2683e8a9}]]></GPODomainGuid><GPODomainController><![CDATA[dc02.bcl.nu]]></GPODomainController><BackupTime><![CDATA[2021-02-05T11:27:36]]></BackupTime><ID><![CDATA[{AF32587F-28C1-413F-B45F-A1624D956184}]]></ID><Comment><![CDATA[]]></Comment><GPODisplayName><![CDATA[Bcl - Computer - Block Untrusted Fonts]]></GPODisplayName></BackupInst><BackupInst><GPOGuid><![CDATA[{1caf2f91-f296-42a1-af0e-a90370435b69}]]></GPOGuid><GPODomain><![CDATA[bcl.nu]]></GPODomain><GPODomainGuid><![CDATA[{f5c5e011-a444-44d5-8809-c86e2683e8a9}]]></GPODomainGuid><GPODomainController><![CDATA[dc02.bcl.nu]]></GPODomainController><BackupTime><![CDATA[2021-02-05T11:27:36]]></BackupTime><ID><![CDATA[{2D1A5AFE-775F-4A4F-BC22-88B10C627D29}]]></ID><Comment><![CDATA[]]></Comment><GPODisplayName><![CDATA[Bcl - Computer - Firewall - Rules]]></GPODisplayName></BackupInst><BackupInst><GPOGuid><![CDATA[{1c2ac8b7-dc11-4fdf-bc90-d5e43461092f}]]></GPOGuid><GPODomain><![CDATA[bcl.nu]]></GPODomain><GPODomainGuid><![CDATA[{f5c5e011-a444-44d5-8809-c86e2683e8a9}]]></GPODomainGuid><GPODomainController><![CDATA[dc02.bcl.nu]]></GPODomainController><BackupTime><![CDATA[2021-02-05T11:27:35]]></BackupTime><ID><![CDATA[{AC0906D4-9458-43CA-B91D-4D6C010158C4}]]></ID><Comment><![CDATA[]]></Comment><GPODisplayName><![CDATA[Bcl - Domain Controller - Firewall - IPSec - Any - Request]]></GPODisplayName></BackupInst><BackupInst><GPOGuid><![CDATA[{1bd41502-4e64-4c11-8b9f-276c348df206}]]></GPOGuid><GPODomain><![CDATA[bcl.nu]]></GPODomain><GPODomainGuid><![CDATA[{f5c5e011-a444-44d5-8809-c86e2683e8a9}]]></GPODomainGuid><GPODomainController><![CDATA[dc02.bcl.nu]]></GPODomainController><BackupTime><![CDATA[2021-02-05T11:27:29]]></BackupTime><ID><![CDATA[{798B24A4-C3D9-4EBF-8E92-D48125472B6C}]]></ID><Comment><![CDATA[]]></Comment><GPODisplayName><![CDATA[Bcl - Computer - Display Settings]]></GPODisplayName></BackupInst><BackupInst><GPOGuid><![CDATA[{16c91edd-c5a7-4c72-85ef-7644a758c50d}]]></GPOGuid><GPODomain><![CDATA[bcl.nu]]></GPODomain><GPODomainGuid><![CDATA[{f5c5e011-a444-44d5-8809-c86e2683e8a9}]]></GPODomainGuid><GPODomainController><![CDATA[dc02.bcl.nu]]></GPODomainController><BackupTime><![CDATA[2021-02-05T11:27:29]]></BackupTime><ID><![CDATA[{828BFB77-65F9-4CC9-A9E9-7E52428F2B7A}]]></ID><Comment><![CDATA[]]></Comment><GPODisplayName><![CDATA[Bcl - Computer - Local Groups]]></GPODisplayName></BackupInst><BackupInst><GPOGuid><![CDATA[{017d10fc-6291-4049-8db9-34c27ec262b1}]]></GPOGuid><GPODomain><![CDATA[bcl.nu]]></GPODomain><GPODomainGuid><![CDATA[{f5c5e011-a444-44d5-8809-c86e2683e8a9}]]></GPODomainGuid><GPODomainController><![CDATA[dc02.bcl.nu]]></GPODomainController><BackupTime><![CDATA[2021-02-05T11:27:25]]></BackupTime><ID><![CDATA[{B90F0648-83F5-4F56-8C9B-F3C02632AA3C}]]></ID><Comment><![CDATA[]]></Comment><GPODisplayName><![CDATA[Bcl - Domain - Clear Deny log on through Terminal Services]]></GPODisplayName></BackupInst></Backups>