<Backups xmlns="http://www.microsoft.com/GroupPolicy/GPOOperations/Manifest" xmlns:mfst="http://www.microsoft.com/GroupPolicy/GPOOperations/Manifest" mfst:version="1.0"><BackupInst><GPOGuid><![CDATA[{197a224f-507c-48f1-afee-38c757b5dd7e}]]></GPOGuid><GPODomain><![CDATA[work.bcl.nu]]></GPODomain><GPODomainGuid><![CDATA[{2e8695ee-4691-4b4a-9757-4bcfe4d5c3e7}]]></GPODomainGuid><GPODomainController><![CDATA[DC01.work.bcl.nu]]></GPODomainController><BackupTime><![CDATA[2024-06-26T13:26:35]]></BackupTime><ID><![CDATA[{893F8B48-77A0-4ACB-B63F-829BCA65E955}]]></ID><Comment><![CDATA[]]></Comment><GPODisplayName><![CDATA[Work - Firewall - Block SMB In]]></GPODisplayName></BackupInst></Backups>