<Backups xmlns="http://www.microsoft.com/GroupPolicy/GPOOperations/Manifest" xmlns:mfst="http://www.microsoft.com/GroupPolicy/GPOOperations/Manifest" mfst:version="1.0"><BackupInst><GPOGuid><![CDATA[{95df675b-0cbe-4334-bb4b-1d5e98c46ea3}]]></GPOGuid><GPODomain><![CDATA[work.bcl.nu]]></GPODomain><GPODomainGuid><![CDATA[{2e8695ee-4691-4b4a-9757-4bcfe4d5c3e7}]]></GPODomainGuid><GPODomainController><![CDATA[DC01.work.bcl.nu]]></GPODomainController><BackupTime><![CDATA[2024-06-26T13:26:40]]></BackupTime><ID><![CDATA[{51CC5163-DB37-420D-B5C2-1E9999CC69DA}]]></ID><Comment><![CDATA[]]></Comment><GPODisplayName><![CDATA[Work - Domain Admin - PAW - Restrict User Rights Assignment]]></GPODisplayName></BackupInst></Backups>