<BackupInst xmlns="http://www.microsoft.com/GroupPolicy/GPOOperations/Manifest"><GPOGuid><![CDATA[{32b021c5-5396-49fd-9d4a-aaaae2333fb7}]]></GPOGuid><GPODomain><![CDATA[bcl.nu]]></GPODomain><GPODomainGuid><![CDATA[{f5c5e011-a444-44d5-8809-c86e2683e8a9}]]></GPODomainGuid><GPODomainController><![CDATA[dc02.bcl.nu]]></GPODomainController><BackupTime><![CDATA[2021-01-20T13:02:49]]></BackupTime><ID><![CDATA[{3571CFC0-B9EB-426C-84C1-8CAE625F37CC}]]></ID><Comment><![CDATA[]]></Comment><GPODisplayName><![CDATA[Bcl - Computer - Windows Update]]></GPODisplayName></BackupInst>
